cubicweb_card/__init__.py
cubicweb_card/__pkginfo__.py
cubicweb_card/entities.py
cubicweb_card/hooks.py
cubicweb_card/schema.py
cubicweb_card/site_cubicweb.py
cubicweb_card/uiprops.py
cubicweb_card/data/cubes.card.css
cubicweb_card/i18n/en.po
cubicweb_card/i18n/fr.po
cubicweb_card/migration/0.5.0_Any.py
cubicweb_card/migration/postcreate.py
cubicweb_card/views/__init__.py
cubicweb_card/views/controllers.py
cubicweb_card/views/urlrewrite.py
cubicweb_card-2.1.0.dist-info/METADATA
cubicweb_card-2.1.0.dist-info/WHEEL
cubicweb_card-2.1.0.dist-info/entry_points.txt
cubicweb_card-2.1.0.dist-info/top_level.txt
cubicweb_card-2.1.0.dist-info/RECORD
